{
	"generator_info": "Shape definitions generated with PhysicsEditor. Visit https://www.codeandweb.com/physicseditor",
	"bridge-upper": {
		"type": "fromPhysicsEditor",
		"label": "bridge-upper",
		"isStatic": false,
		"density": 100,
		"restitution": 0,
		"friction": 0.1,
		"frictionAir": 0.01,
		"frictionStatic": 0.5,
		"collisionFilter": {
			"group": 0,
			"category": 1,
			"mask": 255
		},
		"fixtures": [
			{
				"label": "",
				"isSensor": false,
				"vertices": [
					[ { "x":33, "y":32 }, { "x":64, "y":0 }, { "x":0, "y":0 } ]
				]
			}
		]
	},
	"bridge-lower": {
		"type": "fromPhysicsEditor",
		"label": "bridge-lower",
		"isStatic": false,
		"density": 100,
		"restitution": 0,
		"friction": 0.1,
		"frictionAir": 0.01,
		"frictionStatic": 0.5,
		"collisionFilter": {
			"group": 0,
			"category": 1,
			"mask": 255
		},
		"fixtures": [
			{
				"label": "",
				"isSensor": false,
				"vertices": [
					[ { "x":31, "y":0 }, { "x":0, "y":32 }, { "x":64, "y":32 } ]
				]
			}
		]
	}
}
